README.md
setup.py
AICloudSDK.egg-info/PKG-INFO
AICloudSDK.egg-info/SOURCES.txt
AICloudSDK.egg-info/dependency_links.txt
AICloudSDK.egg-info/requires.txt
AICloudSDK.egg-info/top_level.txt
aicloud/__init__.py
aicloud/batch_detection_service.py
aicloud/cloudapi.py
aicloud/cloudexception.py
aicloud/engine.py
aicloud/json_to_coco.py
aicloud/json_to_mapillary.py
aicloud/json_to_voc.py
aicloud/json_to_voc_copy.py
aicloud/rest.py
aicloud/sample.py
aicloud/settings.py
aicloud/utils.py
aicloud/voc_xml_generator.py
aicloud/datatransform/coco/config.yaml
aicloud/datatransform/coco/json2coco.py
aicloud/datatransform/mapillary/config.yaml
aicloud/datatransform/mapillary/json2mapillary.py
aicloud/datatransform/voc/config.yaml
aicloud/datatransform/voc/json2voc.py
aicloud/datatransform/voc/voc_xml_generator.py
aicloud/datatransform/voc/source/XML_template/voc_template.xml