Metadata-Version: 1.2
Name: AICloudSDK
Version: 1.0.5
Summary: fix json_to_mapillary.py's bug
Home-page: UNKNOWN
Author: liyichao
Author-email: liyichao6852@navinfo.com
License: UNKNOWN
Platform: UNKNOWN
Classifier: Programming Language :: Python :: 3
Classifier: License :: OSI Approved :: MIT License
Classifier: Operating System :: OS Independent
Requires-Python: >=3
